{"canonicalUrl":"https://unitedstats.vercel.app/history-changed/2026-05-09-sunderland-a","claimVersion":"cv1-3c58b33fd0d3fbb1","claims":[{"evidencePath":"/match/2026-05-09-sunderland-a","evidenceUrl":"https://unitedstats.vercel.app/match/2026-05-09-sunderland-a","id":"us:history-digest:2026-05-09-sunderland-a:claim-01-result","kind":"result","text":"Manchester United drew 0–0 with Sunderland away.","title":"Manchester United drew with Sunderland","value":"D"},{"evidencePath":"/match/2026-05-09-sunderland-a","evidenceUrl":"https://unitedstats.vercel.app/match/2026-05-09-sunderland-a","id":"us:history-digest:2026-05-09-sunderland-a:claim-02-streak-ended","kind":"streak-ended","text":"This result snapped a 3-match winning run.","title":"A 3-match winning run ends","value":3},{"evidencePath":"/match/2026-05-09-sunderland-a","evidenceUrl":"https://unitedstats.vercel.app/match/2026-05-09-sunderland-a","id":"us:history-digest:2026-05-09-sunderland-a:claim-03-streak-ended","kind":"streak-ended","text":"This result snapped a 24-match scoring run.","title":"A 24-match scoring run ends","value":24}],"evidenceLinks":[{"label":"Match page","path":"/match/2026-05-09-sunderland-a","url":"https://unitedstats.vercel.app/match/2026-05-09-sunderland-a"},{"label":"API record","path":"/api/v1/matches/2026-05-09-sunderland-a","url":"https://unitedstats.vercel.app/api/v1/matches/2026-05-09-sunderland-a"}],"match":{"competition":"Premier League","date":"2026-05-09","id":"2026-05-09-sunderland-a","manager":"Michael Carrick","opponent":"Sunderland","result":"D","score":"0-0","season":"2025-26","venue":"A"},"matchId":"2026-05-09-sunderland-a","provenance":[{"confidence":"supporting","evidencePath":"/match/2026-05-09-sunderland-a","evidenceUrl":"https://unitedstats.vercel.app/match/2026-05-09-sunderland-a","facet":"attendance","sourceId":"wikipedia","sourceName":"Wikipedia match and season articles","sourceUrl":"https://www.wikipedia.org/"},{"confidence":"supporting","evidencePath":"/match/2026-05-09-sunderland-a","evidenceUrl":"https://unitedstats.vercel.app/match/2026-05-09-sunderland-a","facet":"attendance","sourceId":"openfootball","sourceName":"openfootball","sourceUrl":"https://github.com/openfootball"},{"confidence":"supporting","evidencePath":"/match/2026-05-09-sunderland-a","evidenceUrl":"https://unitedstats.vercel.app/match/2026-05-09-sunderland-a","facet":"attendance","sourceId":"transfermarkt-datasets","sourceName":"transfermarkt-datasets","sourceUrl":"https://github.com/dcaribou/transfermarkt-datasets"},{"confidence":"supporting","evidencePath":"/match/2026-05-09-sunderland-a","evidenceUrl":"https://unitedstats.vercel.app/match/2026-05-09-sunderland-a","facet":"bench","note":"Bench players are listed separately and excluded from appearance totals unless they entered.","sourceId":"wikipedia","sourceName":"Wikipedia match and season articles","sourceUrl":"https://www.wikipedia.org/"},{"confidence":"supporting","evidencePath":"/match/2026-05-09-sunderland-a","evidenceUrl":"https://unitedstats.vercel.app/match/2026-05-09-sunderland-a","facet":"bench","note":"Bench players are listed separately and excluded from appearance totals unless they entered.","sourceId":"openfootball","sourceName":"openfootball","sourceUrl":"https://github.com/openfootball"},{"confidence":"supporting","evidencePath":"/match/2026-05-09-sunderland-a","evidenceUrl":"https://unitedstats.vercel.app/match/2026-05-09-sunderland-a","facet":"bench","note":"Bench players are listed separately and excluded from appearance totals unless they entered.","sourceId":"transfermarkt-datasets","sourceName":"transfermarkt-datasets","sourceUrl":"https://github.com/dcaribou/transfermarkt-datasets"},{"confidence":"partial","evidencePath":"/match/2026-05-09-sunderland-a","evidenceUrl":"https://unitedstats.vercel.app/match/2026-05-09-sunderland-a","facet":"cards","note":"Only cards explicitly present in the source are recorded.","sourceId":"wikipedia","sourceName":"Wikipedia match and season articles","sourceUrl":"https://www.wikipedia.org/"},{"confidence":"partial","evidencePath":"/match/2026-05-09-sunderland-a","evidenceUrl":"https://unitedstats.vercel.app/match/2026-05-09-sunderland-a","facet":"cards","note":"Only cards explicitly present in the source are recorded.","sourceId":"openfootball","sourceName":"openfootball","sourceUrl":"https://github.com/openfootball"},{"confidence":"partial","evidencePath":"/match/2026-05-09-sunderland-a","evidenceUrl":"https://unitedstats.vercel.app/match/2026-05-09-sunderland-a","facet":"cards","note":"Only cards explicitly present in the source are recorded.","sourceId":"transfermarkt-datasets","sourceName":"transfermarkt-datasets","sourceUrl":"https://github.com/dcaribou/transfermarkt-datasets"},{"confidence":"complete","evidencePath":"/match/2026-05-09-sunderland-a","evidenceUrl":"https://unitedstats.vercel.app/match/2026-05-09-sunderland-a","facet":"result","sourceId":"wikipedia","sourceName":"Wikipedia match and season articles","sourceUrl":"https://www.wikipedia.org/"},{"confidence":"complete","evidencePath":"/match/2026-05-09-sunderland-a","evidenceUrl":"https://unitedstats.vercel.app/match/2026-05-09-sunderland-a","facet":"result","sourceId":"openfootball","sourceName":"openfootball","sourceUrl":"https://github.com/openfootball"},{"confidence":"complete","evidencePath":"/match/2026-05-09-sunderland-a","evidenceUrl":"https://unitedstats.vercel.app/match/2026-05-09-sunderland-a","facet":"result","sourceId":"transfermarkt-datasets","sourceName":"transfermarkt-datasets","sourceUrl":"https://github.com/dcaribou/transfermarkt-datasets"},{"confidence":"complete","evidencePath":"/match/2026-05-09-sunderland-a","evidenceUrl":"https://unitedstats.vercel.app/match/2026-05-09-sunderland-a","facet":"starting-lineup","sourceId":"wikipedia","sourceName":"Wikipedia match and season articles","sourceUrl":"https://www.wikipedia.org/"},{"confidence":"complete","evidencePath":"/match/2026-05-09-sunderland-a","evidenceUrl":"https://unitedstats.vercel.app/match/2026-05-09-sunderland-a","facet":"starting-lineup","sourceId":"openfootball","sourceName":"openfootball","sourceUrl":"https://github.com/openfootball"},{"confidence":"complete","evidencePath":"/match/2026-05-09-sunderland-a","evidenceUrl":"https://unitedstats.vercel.app/match/2026-05-09-sunderland-a","facet":"starting-lineup","sourceId":"transfermarkt-datasets","sourceName":"transfermarkt-datasets","sourceUrl":"https://github.com/dcaribou/transfermarkt-datasets"},{"confidence":"complete","evidencePath":"/match/2026-05-09-sunderland-a","evidenceUrl":"https://unitedstats.vercel.app/match/2026-05-09-sunderland-a","facet":"used-substitutes","note":"Substitute appearances are recorded for players who entered the match.","sourceId":"wikipedia","sourceName":"Wikipedia match and season articles","sourceUrl":"https://www.wikipedia.org/"},{"confidence":"complete","evidencePath":"/match/2026-05-09-sunderland-a","evidenceUrl":"https://unitedstats.vercel.app/match/2026-05-09-sunderland-a","facet":"used-substitutes","note":"Substitute appearances are recorded for players who entered the match.","sourceId":"openfootball","sourceName":"openfootball","sourceUrl":"https://github.com/openfootball"},{"confidence":"complete","evidencePath":"/match/2026-05-09-sunderland-a","evidenceUrl":"https://unitedstats.vercel.app/match/2026-05-09-sunderland-a","facet":"used-substitutes","note":"Substitute appearances are recorded for players who entered the match.","sourceId":"transfermarkt-datasets","sourceName":"transfermarkt-datasets","sourceUrl":"https://github.com/dcaribou/transfermarkt-datasets"}],"ref":{"id":"us:history-digest:2026-05-09-sunderland-a","key":"2026-05-09-sunderland-a","kind":"history-digest","path":"/history-changed/2026-05-09-sunderland-a","url":"https://unitedstats.vercel.app/history-changed/2026-05-09-sunderland-a"},"schemaVersion":1}
